Workbook

Sheet Raw_Data
A1: Month | B1: Product | C1: Region | D1: Revenue | E1: Budget Revenue | F1: Units | G1: Average Price | H1: COGS | I1: Operating Expenses | J1: Customers
A2: Jan | B2: AquaCore | C2: East | D2: 820000 | E2: 850000 | F2: 4100 | G2: 200 | H2: 180000 | I2: 330000 | J2: 410
A3: Feb | B3: AquaAI | C3: West | D3: 860000 | E3: 880000 | F3: 2150 | G3: 400 | H3: 190000 | I3: 340000 | J3: 430
A4: Mar | B4: AquaSecure | C4: South | D4: 900000 | E4: 920000 | F4: 1800 | G4: 500 | H4: 205000 | I4: 350000 | J4: 450
A5: Apr | B5: AquaCore | C5: East | D5: 970000 | E5: 950000 | F5: 4850 | G5: 200 | H5: 210000 | I5: 345000 | J5: 485
A6: May | B6: AquaAI | C6: West | D6: 1080000 | E6: 1060000 | F6: 2700 | G6: 400 | H6: 220000 | I6: 350000 | J6: 520
A7: Jun | B7: AquaSecure | C7: South | D7: 1300000 | E7: 1280000 | F7: 2600 | G7: 500 | H7: 230000 | I7: 365000 | J7: 560

Sheet Assumptions
A1: AquaTech FP&A — Model Assumptions
A3: Assumption | B3: Value | C3: Description
A4: Base Case Growth | B4: 0.03 | C4: Monthly forecast growth
A5: Upside Growth | B5: 0.05 | C5: Higher-growth scenario
A6: Downside Growth | B6: 0.01 | C6: Conservative scenario
A7: COGS % of Revenue | B7: 0.23 | C7: Planning assumption
A8: OpEx Growth | B8: 0.02 | C8: Monthly operating expense growth

Sheet Budget_vs_Actual
A1: Month | B1: Actual Revenue | C1: Budget Revenue | D1: Variance | E1: Variance % | F1: Status
A2: Jan | B2: =SUMIF(Raw_Data!$A$2:$A$7,A2,Raw_Data!$D$2:$D$7) | C2: =SUMIF(Raw_Data!$A$2:$A$7,A2,Raw_Data!$E$2:$E$7) | D2: =B2-C2 | E2: =IFERROR(D2/C2,0) | F2: =IF(D2>=0,"Favorable","Unfavorable")
A3: Feb | B3: =SUMIF(Raw_Data!$A$2:$A$7,A3,Raw_Data!$D$2:$D$7) | C3: =SUMIF(Raw_Data!$A$2:$A$7,A3,Raw_Data!$E$2:$E$7) | D3: =B3-C3 | E3: =IFERROR(D3/C3,0) | F3: =IF(D3>=0,"Favorable","Unfavorable")
A4: Mar | B4: =SUMIF(Raw_Data!$A$2:$A$7,A4,Raw_Data!$D$2:$D$7) | C4: =SUMIF(Raw_Data!$A$2:$A$7,A4,Raw_Data!$E$2:$E$7) | D4: =B4-C4 | E4: =IFERROR(D4/C4,0) | F4: =IF(D4>=0,"Favorable","Unfavorable")
A5: Apr | B5: =SUMIF(Raw_Data!$A$2:$A$7,A5,Raw_Data!$D$2:$D$7) | C5: =SUMIF(Raw_Data!$A$2:$A$7,A5,Raw_Data!$E$2:$E$7) | D5: =B5-C5 | E5: =IFERROR(D5/C5,0) | F5: =IF(D5>=0,"Favorable","Unfavorable")
A6: May | B6: =SUMIF(Raw_Data!$A$2:$A$7,A6,Raw_Data!$D$2:$D$7) | C6: =SUMIF(Raw_Data!$A$2:$A$7,A6,Raw_Data!$E$2:$E$7) | D6: =B6-C6 | E6: =IFERROR(D6/C6,0) | F6: =IF(D6>=0,"Favorable","Unfavorable")
A7: Jun | B7: =SUMIF(Raw_Data!$A$2:$A$7,A7,Raw_Data!$D$2:$D$7) | C7: =SUMIF(Raw_Data!$A$2:$A$7,A7,Raw_Data!$E$2:$E$7) | D7: =B7-C7 | E7: =IFERROR(D7/C7,0) | F7: =IF(D7>=0,"Favorable","Unfavorable")
A9: Total | B9: =SUM(B2:B7) | C9: =SUM(C2:C7) | D9: =SUM(D2:D7) | E9: =IFERROR(D9/C9,0)

Sheet P&L
A1: AquaTech FP&A — Profit & Loss
A3: Metric | B3: Jan | C3: Feb | D3: Mar | E3: Apr | F3: May | G3: Jun
A4: Revenue | B4: =SUMIF(Raw_Data!$A$2:$A$7,B$3,Raw_Data!$D$2:$D$7) | C4: =SUMIF(Raw_Data!$A$2:$A$7,C$3,Raw_Data!$D$2:$D$7) | D4: =SUMIF(Raw_Data!$A$2:$A$7,D$3,Raw_Data!$D$2:$D$7) | E4: =SUMIF(Raw_Data!$A$2:$A$7,E$3,Raw_Data!$D$2:$D$7) | F4: =SUMIF(Raw_Data!$A$2:$A$7,F$3,Raw_Data!$D$2:$D$7) | G4: =SUMIF(Raw_Data!$A$2:$A$7,G$3,Raw_Data!$D$2:$D$7)
A5: COGS | B5: =SUMIF(Raw_Data!$A$2:$A$7,B$3,Raw_Data!$H$2:$H$7) | C5: =SUMIF(Raw_Data!$A$2:$A$7,C$3,Raw_Data!$H$2:$H$7) | D5: =SUMIF(Raw_Data!$A$2:$A$7,D$3,Raw_Data!$H$2:$H$7) | E5: =SUMIF(Raw_Data!$A$2:$A$7,E$3,Raw_Data!$H$2:$H$7) | F5: =SUMIF(Raw_Data!$A$2:$A$7,F$3,Raw_Data!$H$2:$H$7) | G5: =SUMIF(Raw_Data!$A$2:$A$7,G$3,Raw_Data!$H$2:$H$7)
A6: Gross Profit | B6: =B4-B5 | C6: =C4-C5 | D6: =D4-D5 | E6: =E4-E5 | F6: =F4-F5 | G6: =G4-G5
A7: Gross Margin | B7: =IFERROR(B6/B4,0) | C7: =IFERROR(C6/C4,0) | D7: =IFERROR(D6/D4,0) | E7: =IFERROR(E6/E4,0) | F7: =IFERROR(F6/F4,0) | G7: =IFERROR(G6/G4,0)
A8: Operating Expenses | B8: =SUMIF(Raw_Data!$A$2:$A$7,B$3,Raw_Data!$I$2:$I$7) | C8: =SUMIF(Raw_Data!$A$2:$A$7,C$3,Raw_Data!$I$2:$I$7) | D8: =SUMIF(Raw_Data!$A$2:$A$7,D$3,Raw_Data!$I$2:$I$7) | E8: =SUMIF(Raw_Data!$A$2:$A$7,E$3,Raw_Data!$I$2:$I$7) | F8: =SUMIF(Raw_Data!$A$2:$A$7,F$3,Raw_Data!$I$2:$I$7) | G8: =SUMIF(Raw_Data!$A$2:$A$7,G$3,Raw_Data!$I$2:$I$7)
A9: Operating Profit | B9: =B6-B8 | C9: =C6-C8 | D9: =D6-D8 | E9: =E6-E8 | F9: =F6-F8 | G9: =G6-G8
A10: Operating Margin | B10: =IFERROR(B9/B4,0) | C10: =IFERROR(C9/C4,0) | D10: =IFERROR(D9/D4,0) | E10: =IFERROR(E9/E4,0) | F10: =IFERROR(F9/F4,0) | G10: =IFERROR(G9/G4,0)

Sheet Forecast_Scenarios
A1: Scenario | B1: Jul Forecast | C1: Aug Forecast | D1: Sep Forecast | E1: Oct Forecast
A2: Base Case | B2: =P&L!G4*(1+Assumptions!B3) | C2: =B2*(1+Assumptions!B3) | D2: =C2*(1+Assumptions!B3) | E2: =D2*(1+Assumptions!B3)
A3: Upside | B3: =P&L!G4*(1+Assumptions!B4) | C3: =B3*(1+Assumptions!B4) | D3: =C3*(1+Assumptions!B4) | E3: =D3*(1+Assumptions!B4)
A4: Downside | B4: =P&L!G4*(1+Assumptions!B5) | C4: =B4*(1+Assumptions!B5) | D4: =C4*(1+Assumptions!B5) | E4: =D4*(1+Assumptions!B5)

Sheet KPIs
A1: AquaTech FP&A — KPI Summary
A3: KPI | B3: Value | C3: Reference | D3: Interpretation
A4: Total Revenue | B4: =SUM(P&L!B4:G4) | C4: Budget = $5.94M | D4: Actual revenue across Jan-Jun
A5: Revenue Variance | B5: =Budget_vs_Actual!D9 | C5: Near 0 | D5: Actual vs budget gap
A6: Gross Margin | B6: =SUM(P&L!B6:G6)/SUM(P&L!B4:G4) | C6: ~75%+ | D6: Gross profitability
A7: Operating Margin | B7: =SUM(P&L!B9:G9)/SUM(P&L!B4:G4) | C7: ~55%+ | D7: Operating profitability
A8: Avg Revenue / Customer | B8: =SUM(Raw_Data!D2:D7)/SUM(Raw_Data!J2:J7) | C8: Monitor trend | D8: Customer monetization

Sheet Executive_Dashboard
A1: AquaTech FP&A — Executive Dashboard
A3: Total Revenue | C3: Revenue Variance | E3: Gross Margin | G3: Operating Margin
A4: =KPIs!B4 | C4: =KPIs!B5 | E4: =KPIs!B6 | G4: =KPIs!B7
